StackoverflowAboutPythonZhongwenban/README.md
StackoverflowAboutPythonZhongwenban/__init__.py
StackoverflowAboutPythonZhongwenban/__main__.py
StackoverflowAboutPythonZhongwenban/file.epub
StackoverflowAboutPythonZhongwenban/index.html
StackoverflowAboutPythonZhongwenban/css/__init__.py
StackoverflowAboutPythonZhongwenban/css/annotations.css
StackoverflowAboutPythonZhongwenban/css/main.css
StackoverflowAboutPythonZhongwenban/css/normalize.css
StackoverflowAboutPythonZhongwenban/css/popup.css
StackoverflowAboutPythonZhongwenban/font/__init__.py
StackoverflowAboutPythonZhongwenban/font/fontello.eot
StackoverflowAboutPythonZhongwenban/font/fontello.svg
StackoverflowAboutPythonZhongwenban/font/fontello.ttf
StackoverflowAboutPythonZhongwenban/font/fontello.woff
StackoverflowAboutPythonZhongwenban/img/__init__.py
StackoverflowAboutPythonZhongwenban/img/annotator-glyph-sprite.png
StackoverflowAboutPythonZhongwenban/img/annotator-icon-sprite.png
StackoverflowAboutPythonZhongwenban/img/apple-touch-icon.png
StackoverflowAboutPythonZhongwenban/img/cancelfullscreen.png
StackoverflowAboutPythonZhongwenban/img/close.png
StackoverflowAboutPythonZhongwenban/img/fullscreen.png
StackoverflowAboutPythonZhongwenban/img/loader.gif
StackoverflowAboutPythonZhongwenban/img/menu-icon.png
StackoverflowAboutPythonZhongwenban/img/save.png
StackoverflowAboutPythonZhongwenban/img/saved.png
StackoverflowAboutPythonZhongwenban/img/settings-s.png
StackoverflowAboutPythonZhongwenban/img/settings.png
StackoverflowAboutPythonZhongwenban/img/star.png
StackoverflowAboutPythonZhongwenban/js/__init__.py
StackoverflowAboutPythonZhongwenban/js/epub.js
StackoverflowAboutPythonZhongwenban/js/epub.min.js
StackoverflowAboutPythonZhongwenban/js/epub.min.map
StackoverflowAboutPythonZhongwenban/js/hooks.min.js
StackoverflowAboutPythonZhongwenban/js/hooks.min.map
StackoverflowAboutPythonZhongwenban/js/reader.js
StackoverflowAboutPythonZhongwenban/js/reader.js.map
StackoverflowAboutPythonZhongwenban/js/reader.min.js
stackoverflow_about_python_zhongwenban-2024.3.4.0.dist-info/METADATA
stackoverflow_about_python_zhongwenban-2024.3.4.0.dist-info/WHEEL
stackoverflow_about_python_zhongwenban-2024.3.4.0.dist-info/entry_points.txt
stackoverflow_about_python_zhongwenban-2024.3.4.0.dist-info/top_level.txt
stackoverflow_about_python_zhongwenban-2024.3.4.0.dist-info/RECORD
